mcgen/__init__.py
mcgen/__main__.py
mcgen/context.py
mcgen/logging.py
mcgen/processors/__init__.py
mcgen/processors/convert_json_files.py
mcgen/processors/create_all_tags_data_pack.py
mcgen/processors/simplify_blocks.py
mcgen/processors/split_registries.py
mcgen/processors/summarize_data.py
mcgen/processors/summarize_worldgen.py
mcgen/processors/write_version_file.py
mcgen/run.py
mcgen/utils.py
mcgen-0.8.0.dist-info/LICENSE.txt
mcgen-0.8.0.dist-info/WHEEL
mcgen-0.8.0.dist-info/METADATA
mcgen-0.8.0.dist-info/RECORD
