Metadata-Version: 2.1
Name: mcgen
Version: 0.8.0
Summary: Python utilities for downloading and processing Minecraft's generated data.
Home-page: https://github.com/Arcensoth/mcgen
License: MIT
Keywords: minecraft,data,mcdata,mcgen
Author: Arcensoth
Author-email: arcensoth@gmail.com
Requires-Python: >=3.8,<4.0
Classifier: License :: OSI Approved :: MIT License
Classifier: Programming Language :: Python :: 3
Classifier: Programming Language :: Python :: 3.8
Classifier: Programming Language :: Python :: 3.9
Classifier: Programming Language :: Python :: 3.10
Provides-Extra: colors
Requires-Dist: colorama (>=0.4.3,<0.5.0); extra == "colors"
Requires-Dist: colorlog (>=4.2.1,<5.0.0); extra == "colors"
Project-URL: Repository, https://github.com/Arcensoth/mcgen
